[
  {
    "eng": "announce",
    "kor": "발표하다"
  },
  {
    "eng": "announcement",
    "kor": "발표"
  },
  {
    "eng": "interested",
    "kor": "관련 있는, 관심이 있는"
  },
  {
    "eng": "interest",
    "kor": "관심"
  },
  {
    "eng": "interesting",
    "kor": "흥미로운"
  },
  {
    "eng": "active",
    "kor": "적극적인, 활발한"
  },
  {
    "eng": "activation",
    "kor": "활성화"
  },
  {
    "eng": "actively",
    "kor": "적극적으로"
  },
  {
    "eng": "accept",
    "kor": "수락하다, 승낙하다"
  },
  {
    "eng": "acceptable",
    "kor": "받아들일 수 있는"
  },
  {
    "eng": "acceptance",
    "kor": "수락"
  },
  {
    "eng": "accepting",
    "kor": "흔쾌히 받아들이는, 솔직한"
  },
  {
    "eng": "acceptably",
    "kor": "받아들일 수 있게"
  },
  {
    "eng": "reject",
    "kor": "거절하다"
  },
  {
    "eng": "foresee",
    "kor": "예견하다, 예감하다"
  },
  {
    "eng": "foreseeable",
    "kor": "예견할 수 있는"
  },
  {
    "eng": "unforeseen",
    "kor": "예측하지 못한, 뜻밖의"
  },
  {
    "eng": "predict",
    "kor": "예측하다"
  },
  {
    "eng": "expansion",
    "kor": "확장, 팽창"
  },
  {
    "eng": "expand",
    "kor": "확장하다"
  },
  {
    "eng": "expansive",
    "kor": "포괄적인, 광범위한"
  },
  {
    "eng": "relocate",
    "kor": "이전하다, 재배치하다"
  },
  {
    "eng": "relocation",
    "kor": "재배치, 이전"
  },
  {
    "eng": "competitor",
    "kor": "경쟁업체, 경쟁자"
  },
  {
    "eng": "asset",
    "kor": "자산"
  },
  {
    "eng": "estate",
    "kor": "재산, 자산"
  },
  {
    "eng": "property",
    "kor": "재산, 자산"
  },
  {
    "eng": "contribute",
    "kor": "기여하다, 공헌하다"
  },
  {
    "eng": "contribution",
    "kor": "기여, 공헌"
  },
  {
    "eng": "contributor",
    "kor": "기여자"
  },
  {
    "eng": "dedicated",
    "kor": "(목표 등에) 전념하는, 헌신적인"
  },
  {
    "eng": "dedicated",
    "kor": "바치다"
  },
  {
    "eng": "dedication",
    "kor": "헌신, 전념"
  },
  {
    "eng": "devoted",
    "kor": "헌신적인"
  },
  {
    "eng": "committed",
    "kor": "헌신적인"
  },
  {
    "eng": "misplace",
    "kor": "잃어버리다, 위치를 잘못 잡다"
  },
  {
    "eng": "considerable",
    "kor": "(정도나 양이) 상당한"
  },
  {
    "eng": "consider",
    "kor": "고려하다"
  },
  {
    "eng": "consideration",
    "kor": "고려"
  },
  {
    "eng": "considerably",
    "kor": "상당히"
  },
  {
    "eng": "substantial",
    "kor": "상당한"
  },
  {
    "eng": "insignificant",
    "kor": "사소한, 미미한"
  },
  {
    "eng": "last",
    "kor": "지속되다, 최근의, 마지막의"
  },
  {
    "eng": "emerge",
    "kor": "부상하다, 나타나다"
  },
  {
    "eng": "emergence",
    "kor": "출현"
  },
  {
    "eng": "emergent",
    "kor": "신생의, 신흥의"
  },
  {
    "eng": "grow",
    "kor": "성장하다, 성장시키다, 증가시키다"
  },
  {
    "eng": "growth",
    "kor": "성장"
  },
  {
    "eng": "develop",
    "kor": "성장하다, 발달하다"
  },
  {
    "eng": "select",
    "kor": "선발하다, 선택하다"
  },
  {
    "eng": "selection",
    "kor": "선발, 선정"
  },
  {
    "eng": "merge",
    "kor": "합병하다, 병합하다"
  },
  {
    "eng": "merger",
    "kor": "합병"
  },
  {
    "eng": "amalgamate",
    "kor": "합병하다"
  },
  {
    "eng": "imply",
    "kor": "암시하다, 넌지시 나타내다, 의미하다"
  },
  {
    "eng": "suggest",
    "kor": "암시하다, 시사하다"
  },
  {
    "eng": "vital",
    "kor": "필수적인"
  },
  {
    "eng": "vitally",
    "kor": "필수적으로, 지극히"
  },
  {
    "eng": "persist",
    "kor": "(집요하게) 계속하다, 계속되다, 지속되다"
  },
  {
    "eng": "persistent",
    "kor": "집요한"
  },
  {
    "eng": "persistence",
    "kor": "끈기, 고집, 지속성"
  },
  {
    "eng": "independent",
    "kor": "독립적인, 독자적인"
  },
  {
    "eng": "dependent",
    "kor": "의존하는"
  },
  {
    "eng": "force",
    "kor": "세력, 강요하다"
  },
  {
    "eng": "establish",
    "kor": "설립하다"
  },
  {
    "eng": "establishment",
    "kor": "설립"
  },
  {
    "eng": "established",
    "kor": "확립된"
  },
  {
    "eng": "initiate",
    "kor": "(사업 등을) 착수하다, 시작하다"
  },
  {
    "eng": "initial",
    "kor": "초기의, 이니셜"
  },
  {
    "eng": "initially",
    "kor": "처음에"
  },
  {
    "eng": "launch",
    "kor": "착수하다"
  },
  {
    "eng": "commence",
    "kor": "착수하다, 시작하다"
  }
]